WhatsappWebKit/Elements.py
WhatsappWebKit/GoogleMeet.py
WhatsappWebKit/Initializer.py
WhatsappWebKit/Locators.py
WhatsappWebKit/Utils.py
WhatsappWebKit/__init__.py
WhatsappWebKit/__pycache__/Elements.cpython-36.pyc
WhatsappWebKit/__pycache__/__init__.cpython-36.pyc
WhatsappWebKit-1.2.0.dist-info/LICENSE
WhatsappWebKit-1.2.0.dist-info/METADATA
WhatsappWebKit-1.2.0.dist-info/WHEEL
WhatsappWebKit-1.2.0.dist-info/top_level.txt
WhatsappWebKit-1.2.0.dist-info/RECORD
