Metadata-Version: 2.1
Name: WhatsappWebKit
Version: 1.2.0
Summary: A small library helpful for manipulating whatsapp web using selenium
Home-page: https://github.com/Devansh-bit/WhatsappWebKit
Author: Devansh Gupta
Author-email: xyznfc@gmail.com
License: MIT
Platform: UNKNOWN
Classifier: Programming Language :: Python :: 3
Classifier: License :: OSI Approved :: MIT License
Classifier: Operating System :: OS Independent
Requires-Dist: selenium
